listenclosely_whatsapp/__init__.py
listenclosely_whatsapp/conf.py
listenclosely_whatsapp/layer.py
listenclosely_whatsapp/service.py
listenclosely_whatsapp-0.1.1.dist-info/DESCRIPTION.rst
listenclosely_whatsapp-0.1.1.dist-info/METADATA
listenclosely_whatsapp-0.1.1.dist-info/RECORD
listenclosely_whatsapp-0.1.1.dist-info/WHEEL
listenclosely_whatsapp-0.1.1.dist-info/metadata.json
listenclosely_whatsapp-0.1.1.dist-info/top_level.txt
