Metadata-Version: 2.0
Name: listenclosely-whatsapp
Version: 0.1.1
Summary: ListenClosely service backend to work with Whatsapp
Home-page: https://github.com/jlmadurga/listenclosely-whatsapp
Author: Juan Madurga
Author-email: jlmadurga@gmail.com
License: ISCL
Keywords: listenclosely-whatsapp
Platform: UNKNOWN
Classifier: Development Status :: 2 - Pre-Alpha
Classifier: Intended Audience :: Developers
Classifier: License :: OSI Approved :: ISC License (ISCL)
Classifier: Natural Language :: English
Classifier: Programming Language :: Python :: 2
Classifier: Programming Language :: Python :: 2.7
Classifier: Programming Language :: Python :: 3
Classifier: Programming Language :: Python :: 3.3
Classifier: Programming Language :: Python :: 3.4
Classifier: Programming Language :: Python :: 3.5
Requires-Dist: listenclosely (==0.1.2)
Requires-Dist: yowsup-celery (==0.2.1)
